ppqs-2.4.0.dist-info/licenses/LICENSES/MIT.txt
py_proj_quick_scripts/__init__.py
ppqs-2.4.0.dist-info/METADATA
ppqs-2.4.0.dist-info/WHEEL
ppqs-2.4.0.dist-info/entry_points.txt
ppqs-2.4.0.dist-info/top_level.txt
ppqs-2.4.0.dist-info/RECORD
