Metadata-Version: 2.4
Name: ppqs
Version: 2.4.0
Summary: Python project quick scripts
Author-email: Karl Wette <karl.wette@anu.edu.au>
License-Expression: MIT
Project-URL: Homepage, https://github.com/kwwette/ppqs
Project-URL: Issues, https://github.com/kwwette/ppqs/issues
Classifier: Programming Language :: Python :: 3
Classifier: Operating System :: OS Independent
Requires-Python: >=3.9
License-File: LICENSES/MIT.txt
Requires-Dist: tomli>=1.1.0; python_version < "3.11"
Dynamic: license-file
